matomo_sdk_py/__init__.py
matomo_sdk_py/matomo_sdk_py.py
matomo_sdk_py/test_matomoSdkPy.py
matomo_sdk_py-0.2.1.dist-info/LICENSE
matomo_sdk_py-0.2.1.dist-info/METADATA
matomo_sdk_py-0.2.1.dist-info/WHEEL
matomo_sdk_py-0.2.1.dist-info/top_level.txt
matomo_sdk_py-0.2.1.dist-info/RECORD
