Metadata-Version: 2.1
Name: matomo-sdk-py
Version: 0.2.1
Summary: Python SDK to send POST http requests to matomo
Home-page: https://gitlab.com/autofitcloud/matomoSdkPy
Author: Shadi Akiki, AutofitCloud
Author-email: shadi@autofitcloud.com
License: UNKNOWN
Platform: UNKNOWN
Requires-Dist: requests (==2.22.0)
